riot_pal/__init__.py
riot_pal/base_device.py
riot_pal/dut_shell.py
riot_pal/ll_mem_map_if.py
riot_pal/ll_shell.py
riot_pal/riot_driver.py
riot_pal/serial_driver.py
riot_pal/mem_map/philip_mem_map.csv
riot_pal-0.2.2.dist-info/METADATA
riot_pal-0.2.2.dist-info/RECORD
riot_pal-0.2.2.dist-info/WHEEL
riot_pal-0.2.2.dist-info/top_level.txt
