Metadata-Version: 2.1
Name: riot-pal
Version: 0.2.2
Summary: A protocol abstraction layer for RIOT and low level devices
Home-page: https://github.com/RIOT-OS
Author: RIOT OS
Author-email: devel@riot-os.org
License: MIT
Platform: any
Classifier: Programming Language :: Python :: 3
Classifier: License :: OSI Approved :: MIT License
Classifier: Operating System :: OS Independent
Classifier: Development Status :: 2 - Pre-Alpha
Classifier: Intended Audience :: Developers
Requires-Python: >=3.4.*
Requires-Dist: pyserial
